fluent_contents/__init__.py
fluent_contents/analyzer.py
fluent_contents/appsettings.py
fluent_contents/cache.py
fluent_contents/middleware.py
fluent_contents/panels.py
fluent_contents/admin/__init__.py
fluent_contents/admin/contentitems.py
fluent_contents/admin/genericextensions.py
fluent_contents/admin/placeholdereditor.py
fluent_contents/admin/placeholderfield.py
fluent_contents/conf/plugin_template/__init__.py
fluent_contents/conf/plugin_template/content_plugins.py
fluent_contents/conf/plugin_template/models.py
fluent_contents/conf/plugin_template/tests.py
fluent_contents/conf/plugin_template/migrations/__init__.py
fluent_contents/extensions/__init__.py
fluent_contents/extensions/model_fields.py
fluent_contents/extensions/pluginbase.py
fluent_contents/extensions/pluginpool.py
fluent_contents/forms/__init__.py
fluent_contents/forms/fields.py
fluent_contents/forms/widgets.py
fluent_contents/locale/en/LC_MESSAGES/django.mo
fluent_contents/locale/en/LC_MESSAGES/django.po
fluent_contents/locale/nl/LC_MESSAGES/django.mo
fluent_contents/locale/nl/LC_MESSAGES/django.po
fluent_contents/management/__init__.py
fluent_contents/management/commands/__init__.py
fluent_contents/management/commands/find_contentitem_urls.py
fluent_contents/management/commands/prefix_content_item_types.py
fluent_contents/management/commands/remove_stale_contentitems.py
fluent_contents/management/commands/start_content_plugin.py
fluent_contents/migrations/0001_initial.py
fluent_contents/migrations/__init__.py
fluent_contents/models/__init__.py
fluent_contents/models/db.py
fluent_contents/models/fields.py
fluent_contents/models/managers.py
fluent_contents/models/mixins.py
fluent_contents/plugins/__init__.py
fluent_contents/plugins/code/__init__.py
fluent_contents/plugins/code/appsettings.py
fluent_contents/plugins/code/backend.py
fluent_contents/plugins/code/content_plugins.py
fluent_contents/plugins/code/models.py
fluent_contents/plugins/code/migrations/0001_initial.py
django_fluent_contents-3.1.dist-info/AUTHORS
django_fluent_contents-3.1.dist-info/LICENSE
django_fluent_contents-3.1.dist-info/METADATA
django_fluent_contents-3.1.dist-info/WHEEL
django_fluent_contents-3.1.dist-info/top_level.txt
django_fluent_contents-3.1.dist-info/RECORD
