Metadata-Version: 2.1
Name: django-fluent-contents
Version: 3.1
Summary: A widget engine to display various content on Django pages
Home-page: https://github.com/edoburu/django-fluent-contents
Download-URL: https://github.com/edoburu/django-fluent-contents/zipball/master
Author: Diederik van der Boor
Author-email: opensource@edoburu.nl
License: Apache 2.0
Classifier: Development Status :: 5 - Production/Stable
Classifier: Environment :: Web Environment
Classifier: Framework :: Django
Classifier: Intended Audience :: Developers
Classifier: License :: OSI Approved :: Apache Software License
Classifier: Operating System :: OS Independent
Classifier: Programming Language :: Python
Classifier: Programming Language :: Python :: 3.6
Classifier: Programming Language :: Python :: 3.7
Classifier: Programming Language :: Python :: 3.8
Classifier: Framework :: Django
Classifier: Framework :: Django :: 2.2
Classifier: Framework :: Django :: 3.1
Classifier: Framework :: Django :: 3.2
Classifier: Topic :: Internet :: WWW/HTTP
Classifier: Topic :: Internet :: WWW/HTTP :: Dynamic Content
Classifier: Topic :: Software Development :: Libraries :: Application Frameworks
Classifier: Topic :: Software Development :: Libraries :: Python Modules
Requires: Django (>=2.2)
License-File: LICENSE
License-File: AUTHORS
Requires-Dist: django-fluent-utils >=2.0.0
Requires-Dist: django-parler >=2.0.1
Requires-Dist: django-polymorphic >=2.1.2
Requires-Dist: django-tag-parser >=3.2
Requires-Dist: django-template-analyzer >=1.6.2
Requires-Dist: html5lib >=1.1
Provides-Extra: code
Requires-Dist: Pygments ; extra == 'code'
Provides-Extra: disquscommentsarea
Requires-Dist: django-disqus ; extra == 'disquscommentsarea'
Provides-Extra: formdesignerlink
Requires-Dist: django-form-designer-ai >=1.0.1 ; extra == 'formdesignerlink'
Provides-Extra: markup
Requires-Dist: docutils ; extra == 'markup'
Requires-Dist: textile ; extra == 'markup'
Requires-Dist: Markdown >=1.7 ; extra == 'markup'
Provides-Extra: oembeditem
Requires-Dist: micawber >=0.3.3 ; extra == 'oembeditem'
Requires-Dist: beautifulsoup4 >=4.3.2 ; extra == 'oembeditem'
Provides-Extra: tests
Requires-Dist: django-wysiwyg ; extra == 'tests'
Requires-Dist: html5lib ; extra == 'tests'
Requires-Dist: Pillow ; extra == 'tests'
Requires-Dist: micawber ; extra == 'tests'
Requires-Dist: docutils ; extra == 'tests'
Requires-Dist: textile ; extra == 'tests'
Requires-Dist: MarkDown ; extra == 'tests'
Requires-Dist: pygments ; extra == 'tests'
Requires-Dist: disqus ; extra == 'tests'
Provides-Extra: text
Requires-Dist: django-wysiwyg >=0.7.1 ; extra == 'text'
Provides-Extra: twitterfeed
Requires-Dist: twitter-text >=3.0 ; extra == 'twitterfeed'
